scrapy_do/__init__.py
scrapy_do/app.py
scrapy_do/config.py
scrapy_do/controller.py
scrapy_do/default.conf
scrapy_do/schedule.py
scrapy_do/utils.py
scrapy_do/webservice.py
scrapy_do/websocket.py
scrapy_do/client/__init__.py
scrapy_do/client/archive.py
scrapy_do/client/commands.py
scrapy_do/client/webclient.py
scrapy_do/ui/asset-manifest.json
scrapy_do/ui/favicon.png
scrapy_do/ui/index.html
scrapy_do/ui/manifest.json
scrapy_do/ui/scrapy-do-logo.png
scrapy_do/ui/static/css/2.2c75a51b.chunk.css
scrapy_do/ui/static/css/2.2c75a51b.chunk.css.map
scrapy_do/ui/static/css/main.739dce30.chunk.css
scrapy_do/ui/static/css/main.739dce30.chunk.css.map
scrapy_do/ui/static/js/2.43dc11c3.chunk.js
scrapy_do/ui/static/js/2.43dc11c3.chunk.js.LICENSE.txt
scrapy_do/ui/static/js/2.43dc11c3.chunk.js.map
scrapy_do/ui/static/js/main.05437ca2.chunk.js
scrapy_do/ui/static/js/main.05437ca2.chunk.js.map
scrapy_do/ui/static/js/runtime-main.d8cead18.js
scrapy_do/ui/static/js/runtime-main.d8cead18.js.map
scrapy_do-0.5.0.data/scripts/scrapy-do
scrapy_do-0.5.0.data/scripts/scrapy-do-cl
scrapy_do-0.5.0.dist-info/LICENSE
scrapy_do-0.5.0.dist-info/METADATA
scrapy_do-0.5.0.dist-info/WHEEL
scrapy_do-0.5.0.dist-info/top_level.txt
scrapy_do-0.5.0.dist-info/RECORD
